Metadata-Version: 1.0
Name: tpletzerDistributions
Version: 1.0
Summary: Gaussian and Binomial distributions
Home-page: UNKNOWN
Author: Tamara Pletzer
Author-email: tamara.pletzer@gmail.com
License: UNKNOWN
Platform: UNKNOWN
